{"characters":[],"episodes":[{"id":11055753,"seriesId":362829,"name":"Side Quest: Song and Dance","aired":"2025-03-26","runtime":28,"overview":"Phil, the art director of MQ, attempts to enjoy a Hawaiian vacation with his girlfriend while dealing with increasingly invasive calls from Ian Grimm.","image":"/banners/v4/episode/11055753/screencap/6802d2c3b7433.jpg","imageType":11,"isMovie":0,"number":1,"seasonNumber":0,"lastUpdated":"2025-04-18 22:31:33","characters":[]},{"id":11055754,"seriesId":362829,"name":"Side Quest: Pull List","aired":"2025-03-26","runtime":29,"overview":"When a Black-owned comic book shop receives only one copy of the latest MQ comic, five superfans fight over who deserves it the most.","image":"/banners/v4/episode/11055754/screencap/6802d3318368e.jpg","imageType":11,"isMovie":0,"number":2,"seasonNumber":0,"lastUpdated":"2025-04-18 22:33:23","characters":[]},{"id":11055755,"seriesId":362829,"name":"Side Quest: Fugue","aired":"2025-03-26","runtime":34,"overview":"A young cellist joins a touring video game orchestra, only to discover what happens when your dream job becomes a nightmare.","image":"/banners/v4/episode/11055755/screencap/6802d36540100.jpg","imageType":11,"isMovie":0,"number":3,"seasonNumber":0,"lastUpdated":"2025-04-18 22:34:15","characters":[]},{"id":11055756,"seriesId":362829,"name":"Side Quest: The Last Raid","aired":"2025-03-26","runtime":27,"overview":"Five high school friends in a long-running MQ guild discover a glitch that might break the game—or their friendship.","image":"/banners/v4/episode/11055756/screencap/6802d38bc555b.jpg","imageType":11,"isMovie":0,"number":4,"seasonNumber":0,"lastUpdated":"2025-04-18 22:34:53","characters":[]},{"id":11091719,"seriesId":362829,"name":"Heaven and Hell (Original Cut)","aired":"2025-03-26","runtime":25,"overview":"An unexpected visitor from Montreal evaluates MQ. Ian and Poppy face a pivotal decision. The original season finale cut serves as the alternate cut according to Apple+ current lineup.","image":"/banners/v4/episode/11091719/screencap/68029c2ca1939.jpg","imageType":11,"isMovie":0,"number":5,"seasonNumber":0,"lastUpdated":"2025-04-22 05:16:51","finaleType":"series","airsAfterSeason":4,"characters":[]},{"id":7501639,"seriesId":362829,"name":"Pilot","aired":"2020-02-07","runtime":28,"overview":"As the hit video game Mythic Quest prepares to launch its newest update, creator Ian Grimm obsesses over a seemingly minor detail.","image":"/banners/series/362829/episodes/62074819.jpg","imageType":11,"isMovie":0,"number":1,"seasonNumber":1,"lastUpdated":"2024-07-08 07:05:09","characters":[]},{"id":7501859,"seriesId":362829,"name":"The Casino","aired":"2020-02-07","runtime":24,"overview":"Brad takes the day off to prove a point, leaving Poppy and David to keep the game afloat. Dana and Rachel have a girls’ night in.","image":"/banners/series/362829/episodes/62074820.jpg","imageType":11,"isMovie":0,"number":2,"seasonNumber":1,"lastUpdated":"2024-07-08 07:05:20","characters":[]},{"id":7501860,"seriesId":362829,"name":"Dinner Party","aired":"2020-02-07","runtime":24,"overview":"The development team must take decisive action when the internet discovers a dark group of gamers congregating in Mythic Quest.","image":"/banners/series/362829/episodes/62074821.jpg","imageType":11,"isMovie":0,"number":3,"seasonNumber":1,"lastUpdated":"2024-07-08 07:05:29","characters":[]},{"id":7501870,"seriesId":362829,"name":"The Convention","aired":"2020-02-07","runtime":30,"overview":"When Pootie_Shoe announces that he’s no longer playing Mythic Quest, the team needs to find a new star streamer to promote it.","image":"/banners/series/362829/episodes/62074822.jpg","imageType":11,"isMovie":0,"number":4,"seasonNumber":1,"lastUpdated":"2024-07-08 07:05:41","characters":[]},{"id":7501871,"seriesId":362829,"name":"A Dark Quiet Death","aired":"2020-02-07","runtime":35,"overview":"From inception to demise, the life cycle of video game Dark Quiet Death.","image":"/banners/series/362829/episodes/62074823.jpg","imageType":11,"isMovie":0,"number":5,"seasonNumber":1,"lastUpdated":"2024-07-08 07:06:16","characters":[]},{"id":7501872,"seriesId":362829,"name":"Non-Player Character","aired":"2020-02-07","runtime":26,"overview":"Poppy steps out for a meeting and Mythic Quest headquarters descends into chaos.","image":"/banners/series/362829/episodes/62074824.jpg","imageType":11,"isMovie":0,"number":6,"seasonNumber":1,"lastUpdated":"2024-07-08 07:06:27","characters":[]},{"id":7501873,"seriesId":362829,"name":"Permadeath","aired":"2020-02-07","runtime":29,"overview":"Ian challenges a hacker to an epic in-game showdown.","image":"/banners/series/362829/episodes/62074825.jpg","imageType":11,"isMovie":0,"number":7,"seasonNumber":1,"lastUpdated":"2024-07-08 07:06:36","characters":[]},{"id":7501874,"seriesId":362829,"name":"Brendan","aired":"2020-02-07","runtime":31,"overview":"As Poppy weighs a difficult decision, Ian whisks her away on a mysterious road trip.","image":"/banners/series/362829/episodes/62074826.jpg","imageType":11,"isMovie":0,"number":8,"seasonNumber":1,"lastUpdated":"2024-07-08 07:06:44","characters":[]},{"id":7501875,"seriesId":362829,"name":"Blood Ocean","aired":"2020-02-07","runtime":30,"overview":"With his workforce unionizing, Ian faces a looming departure, the game’s future, and the meaning of two words: Blood Ocean.","image":"/banners/series/362829/episodes/62074827.jpg","imageType":11,"isMovie":0,"number":9,"seasonNumber":1,"lastUpdated":"2025-01-27 19:26:18","finaleType":"midseason","characters":[]},{"id":7744183,"seriesId":362829,"name":"Quarantine","aired":"2020-05-22","runtime":25,"overview":"As the MQ staff works from home, Poppy struggles with solitude while Brad and David start a charitable competition.","image":"/banners/series/362829/episodes/5ec75eb5ab1e9.jpg","imageType":11,"isMovie":0,"number":10,"seasonNumber":1,"lastUpdated":"2023-02-07 10:14:26","characters":[]},{"id":8337219,"seriesId":362829,"name":"Everlight","aired":"2021-04-16","runtime":32,"overview":"The team returns to the office for their annual Everlight party. Poppy and Ian rig a LARP tournament in an underdog's favor.","image":"/banners/v4/episode/8337219/screencap/607ab16eab95a.jpg","imageType":11,"isMovie":0,"number":11,"seasonNumber":1,"lastUpdated":"2023-02-07 10:16:09","finaleType":"season","characters":[]},{"id":8222945,"seriesId":362829,"name":"Titans’ Rift","aired":"2021-05-07","runtime":25,"overview":"With Ian on sabbatical, Poppy must come up with a title for the new expansion. Dana and Rachel take their relationship to new heights.","image":"/banners/v4/episode/8222945/screencap/608540798cd30.jpg","imageType":11,"isMovie":0,"number":1,"seasonNumber":2,"lastUpdated":"2024-07-08 07:07:54","characters":[]},{"id":8364214,"seriesId":362829,"name":"Grouchy Goat","aired":"2021-05-07","runtime":27,"overview":"Brad wants to launch a mobile game. Poppy is pulled away from working on the expansion with Ian to speak at a luncheon for women in gaming.","image":"/banners/v4/episode/8364214/screencap/6085407a53265.jpg","imageType":11,"isMovie":0,"number":2,"seasonNumber":2,"lastUpdated":"2024-07-08 07:08:05","characters":[]},{"id":8364215,"seriesId":362829,"name":"#YumYum","aired":"2021-05-14","runtime":27,"overview":"Ian and Poppy work separately on the expansion, Jo helps C.W. deal with his publisher, and Brad sets out to find a romantic partner for David.","image":"/banners/v4/episode/8364215/screencap/609aa8f407bef.jpg","imageType":11,"isMovie":0,"number":3,"seasonNumber":2,"lastUpdated":"2024-07-08 07:08:15","characters":[]},{"id":8420368,"seriesId":362829,"name":"Breaking Brad","aired":"2021-05-21","runtime":24,"overview":"Brad attempts to convince the development team that his brother Zack is not the nice guy he’s pretending to be. Rachel does Ian a favor.","image":"/banners/v4/episode/8420368/screencap/60a67a6451a35.jpg","imageType":11,"isMovie":0,"number":4,"seasonNumber":2,"lastUpdated":"2024-07-08 07:08:25","characters":[]},{"id":8420370,"seriesId":362829,"name":"Please Sign Here","aired":"2021-05-28","runtime":26,"overview":"Carol tries to wrangle Mythic Quest employees as they refuse to sign the results of a simple workplace assessment.","image":"/banners/v4/episode/8420370/screencap/60ae5d1adb564.jpg","imageType":11,"isMovie":0,"number":5,"seasonNumber":2,"lastUpdated":"2023-02-07 10:25:44","characters":[]},{"id":8420369,"seriesId":362829,"name":"Backstory!","aired":"2021-06-04","runtime":37,"overview":"A fresh-faced young man discovers what it takes to become one of the world’s greatest science fiction writers.","image":"/banners/v4/episode/8420369/screencap/60a76e6babe24.jpg","imageType":11,"isMovie":0,"number":6,"seasonNumber":2,"lastUpdated":"2023-02-07 10:27:18","characters":[]},{"id":8420371,"seriesId":362829,"name":"Peter","aired":"2021-06-11","runtime":30,"overview":"Rachel accompanies C.W. on an acrimonious visit to his former friend turned rival.","image":"/banners/v4/episode/8420371/screencap/60c0bba9e119a.jpg","imageType":11,"isMovie":0,"number":7,"seasonNumber":2,"lastUpdated":"2024-07-08 07:08:51","characters":[]},{"id":8420372,"seriesId":362829,"name":"Juice Box","aired":"2021-06-18","runtime":24,"overview":"Ian presents his half of the expansion and ends up in the hospital. David ponders his legacy.","image":"/banners/v4/episode/8420372/screencap/60c4f9d4a86c1.jpg","imageType":11,"isMovie":0,"number":8,"seasonNumber":2,"lastUpdated":"2024-07-08 07:09:00","characters":[]},{"id":8420373,"seriesId":362829,"name":"TBD","aired":"2021-06-25","runtime":29,"overview":"Ian and Poppy collaborate again, Rachel and Dana figure out their next move, and Brad looks to settle a feud once and for all.","image":"/banners/v4/episode/8420373/screencap/60cfbb20d1c76.jpg","imageType":11,"isMovie":0,"number":9,"seasonNumber":2,"lastUpdated":"2025-04-08 00:23:39","finaleType":"season","characters":[]},{"id":9372834,"seriesId":362829,"name":"Across the Universe","aired":"2022-11-11","runtime":26,"overview":"As David stewards Mythic Quest, Ian and Poppy consider offers for their offshoot game. Jo assembles the entire team for C.W.’s celebration.","image":"/banners/v4/episode/9372834/screencap/6370d79b40aa3.jpg","imageType":11,"isMovie":0,"number":1,"seasonNumber":3,"lastUpdated":"2023-02-07 10:43:19","characters":[]},{"id":9376686,"seriesId":362829,"name":"Partners","aired":"2022-11-11","runtime":23,"overview":"Ian feels adrift in his new partnership with Poppy. David and Jo are suspicious of an employee’s return. Dana and Rachel meet the new testers.","image":"/banners/v4/episode/9376686/screencap/6370d7ac05822.jpg","imageType":11,"isMovie":0,"number":2,"seasonNumber":3,"lastUpdated":"2023-02-07 10:44:10","characters":[]},{"id":9376687,"seriesId":362829,"name":"Crushing It","aired":"2022-11-18","runtime":24,"overview":"David uses exciting news about MQ to make Ian jealous. Poppy, Rachel, and Jo go to brunch.","image":"/banners/v4/episode/9376687/screencap/6370d7bd74d1d.jpg","imageType":11,"isMovie":0,"number":3,"seasonNumber":3,"lastUpdated":"2023-02-07 10:45:42","characters":[]},{"id":9376688,"seriesId":362829,"name":"The Two Joes","aired":"2022-11-23","runtime":22,"overview":"When David gets stuck in traffic, Jo takes his place to meet with a famous actor for the movie. Brad tries to help Carol raise money through NFTs.","image":"/banners/v4/episode/9376688/screencap/6383439109888.jpg","imageType":11,"isMovie":0,"number":4,"seasonNumber":3,"lastUpdated":"2023-02-07 10:47:53","characters":[]},{"id":9376690,"seriesId":362829,"name":"Playpen","aired":"2022-12-02","runtime":23,"overview":"Poppy begrudgingly takes feedback from Dana about her work. Carol, Brad, and Rachel navigate the aftermath of their monetization gambit.","image":"/banners/v4/episode/9376690/screencap/638343a9d36f8.jpg","imageType":11,"isMovie":0,"number":5,"seasonNumber":3,"lastUpdated":"2023-02-07 10:49:39","characters":[]},{"id":9376691,"seriesId":362829,"name":"The 12 Hours of Christmas","aired":"2022-12-09","runtime":26,"overview":"In the first holiday season since Ian and Poppy’s departure, David grabs the reins and tries to infuse the team with Christmas spirit.","image":"/banners/v4/episode/9376691/screencap/63960e296833b.jpg","imageType":11,"isMovie":0,"number":6,"seasonNumber":3,"lastUpdated":"2023-02-07 10:50:32","characters":[]},{"id":9376692,"seriesId":362829,"name":"Sarian","aired":"2022-12-16","runtime":28,"overview":"Two kids from across the globe find their passions in a world that doesn’t understand them.","image":"/banners/v4/episode/9376692/screencap/63960e3a8a6c7.jpg","imageType":11,"isMovie":0,"number":7,"seasonNumber":3,"lastUpdated":"2023-02-07 10:52:41","characters":[]},{"id":9376693,"seriesId":362829,"name":"To Catch a Mouse","aired":"2022-12-23","runtime":23,"overview":"Ian’s and Poppy’s clashing office preferences put them at odds. Jo and Brad team up to get rid of a pest in David’s office.","image":"/banners/v4/episode/9376693/screencap/63bacdffe87b1.jpg","imageType":11,"isMovie":0,"number":8,"seasonNumber":3,"lastUpdated":"2023-02-07 10:54:34","characters":[]},{"id":9376694,"seriesId":362829,"name":"The Year of Phil","aired":"2022-12-30","runtime":22,"overview":"David’s motion-capture session with Joe Manganiello gets hijacked. Dana helps Poppy prepare her PlayPen VC pitch.","image":"/banners/v4/episode/9376694/screencap/63bace10aa664.jpg","imageType":11,"isMovie":0,"number":9,"seasonNumber":3,"lastUpdated":"2023-05-18 19:25:19","characters":[]},{"id":9376695,"seriesId":362829,"name":"Buffalo Chicken Pizza","aired":"2023-01-06","runtime":27,"overview":"Ian tries to repair his partnership with Poppy. David hits an impasse with the movie. Dana has a realization about Grimpop.","image":"/banners/v4/episode/9376695/screencap/63bace56f3147.jpg","imageType":11,"isMovie":0,"number":10,"seasonNumber":3,"lastUpdated":"2023-05-18 19:25:19","finaleType":"season","characters":[]},{"id":10889551,"seriesId":362829,"name":"Boundaries","aired":"2025-01-29","runtime":26,"overview":"Ian and Poppy reveal their project as they struggle with personal and professional lines. The Mythic Quest team adjusts to their new game’s growth.","image":"/banners/v4/episode/10889551/screencap/677de5449afc3.jpg","imageType":11,"isMovie":0,"number":1,"seasonNumber":4,"lastUpdated":"2025-04-08 01:06:13","characters":[]},{"id":10889552,"seriesId":362829,"name":"1000%","aired":"2025-01-29","runtime":25,"overview":"David uses AI to help regulate gamer behavior—then needs humans to regulate the AI. Meanwhile, no one is regulating Ian and Poppy’s arguments.","image":"/banners/v4/episode/10889552/screencap/677de58d75a06.jpg","imageType":11,"isMovie":0,"number":2,"seasonNumber":4,"lastUpdated":"2025-04-08 01:06:38","characters":[]},{"id":10889553,"seriesId":362829,"name":"Breakthrough","aired":"2025-02-05","runtime":25,"overview":"Ian, David, and Jo embark on a day of self-discovery. Brad teaches Dana and Rachel about financial responsibility.","image":"/banners/v4/episode/10889553/screencap/67998c9e33154.jpg","imageType":11,"isMovie":0,"number":3,"seasonNumber":4,"lastUpdated":"2025-04-08 01:06:46","characters":[]},{"id":10889554,"seriesId":362829,"name":"The Villain’s Feast","aired":"2025-02-12","runtime":33,"overview":"A mysterious host invites the MQ team to a glamorous murder mystery party on a private island.","image":"/banners/v4/episode/10889554/screencap/679ba2cb5f375.jpg","imageType":11,"isMovie":0,"number":4,"seasonNumber":4,"lastUpdated":"2025-04-08 01:06:56","characters":[]},{"id":10889555,"seriesId":362829,"name":"Second Skeleton","aired":"2025-02-19","runtime":27,"overview":"Poppy grapples with a discovery as Ian tries to help in his own unique way. Dana runs into unexpected competition.","image":"/banners/v4/episode/10889555/screencap/67ac01e973808.jpg","imageType":11,"isMovie":0,"number":5,"seasonNumber":4,"lastUpdated":"2025-04-08 01:11:05","characters":[]},{"id":10889556,"seriesId":362829,"name":"The Fish and the Whale","aired":"2025-02-26","runtime":24,"overview":"When Dana’s plans for a new game are threatened by her ties to MQ, Brad devises a long con to help her. Jo throws Poppy a party.","image":"/banners/v4/episode/10889556/screencap/67b53b66d090a.jpg","imageType":11,"isMovie":0,"number":6,"seasonNumber":4,"lastUpdated":"2025-04-08 01:11:14","characters":[]},{"id":10889557,"seriesId":362829,"name":"The Room Where It Happens","aired":"2025-03-05","runtime":28,"overview":"David and Rachel face scrutiny over Playpen. Dana makes a difficult decision. Ian’s attempt to help Poppy doesn’t go as planned.","image":"/banners/v4/episode/10889557/screencap/67be75ed094cd.jpg","imageType":11,"isMovie":0,"number":7,"seasonNumber":4,"lastUpdated":"2025-04-08 01:11:24","characters":[]},{"id":10889558,"seriesId":362829,"name":"Rebrand","aired":"2025-03-12","runtime":28,"overview":"Pootie_Shoe attempts to rebrand himself by challenging a rival to an MMA fight.","image":"/banners/v4/episode/10889558/screencap/67c7b09ec198f.jpg","imageType":11,"isMovie":0,"number":8,"seasonNumber":4,"lastUpdated":"2025-04-08 01:11:48","characters":[]},{"id":10889559,"seriesId":362829,"name":"Telephone","aired":"2025-03-19","runtime":21,"overview":"As Poppy considers a major life change, David scrambles to keep MQ afloat.","image":"/banners/v4/episode/10889559/screencap/67d0ddf6cf0ac.jpg","imageType":11,"isMovie":0,"number":9,"seasonNumber":4,"lastUpdated":"2025-04-08 01:11:55","characters":[]},{"id":10889560,"seriesId":362829,"name":"Heaven and Hell","aired":"2025-03-26","runtime":25,"overview":"An unexpected visitor from Montreal evaluates MQ. Ian and Poppy face a pivotal decision. The updated ending from April 18, 2025 is what Apple TV+ lists as the official series finale after the show's cancelation.","image":"/banners/v4/episode/10889560/screencap/67da1826c5405.jpg","imageType":11,"isMovie":0,"number":10,"seasonNumber":4,"lastUpdated":"2025-05-30 11:15:15","finaleType":"series","characters":[]}]}